pids.py
pids-0.1.2.dist-info/METADATA
pids-0.1.2.dist-info/WHEEL
pids-0.1.2.dist-info/top_level.txt
pids-0.1.2.dist-info/RECORD
